nive_datastore/__init__.py
nive_datastore/app.py
nive_datastore/i18n.py
nive_datastore/item.py
nive_datastore/pydispatch.py
nive_datastore/root.py
nive_datastore/locale/nive_datastore.pot
nive_datastore/locale/de/LC_MESSAGES/nive_datastore.mo
nive_datastore/locale/de/LC_MESSAGES/nive_datastore.po
nive_datastore/scaffolds/__init__.py
nive_datastore/scaffolds/default/CHANGES.txt_tmpl
nive_datastore/scaffolds/default/MANIFEST.in_tmpl
nive_datastore/scaffolds/default/README.txt_tmpl
nive_datastore/scaffolds/default/development.ini_tmpl
nive_datastore/scaffolds/default/production.ini_tmpl
nive_datastore/scaffolds/default/setup.py_tmpl
nive_datastore/scaffolds/default/+package+/__init__.py_tmpl
nive_datastore/scaffolds/default/+package+/tests.py_tmpl
nive_datastore/tests/__init__.py
nive_datastore/tests/__local.py
nive_datastore/tests/db_app.py
nive_datastore/tests/test_app.py
nive_datastore/tests/test_configuration.py
nive_datastore/webapi/__init__.py
nive_datastore/webapi/view.py
nive_datastore/webapi/tests/__init__.py
nive_datastore/webapi/tests/bookmark.pt
nive_datastore/webapi/tests/test_configuration.py
nive_datastore/webapi/tests/test_dispatch.py
nive_datastore/webapi/tests/test_views.py
nive_datastore-1.5.1.dist-info/METADATA
nive_datastore-1.5.1.dist-info/WHEEL
nive_datastore-1.5.1.dist-info/top_level.txt
nive_datastore-1.5.1.dist-info/RECORD
